colors/__init__.py
python_colors_linux-0.3.dist-info/LICENSE
python_colors_linux-0.3.dist-info/METADATA
python_colors_linux-0.3.dist-info/WHEEL
python_colors_linux-0.3.dist-info/top_level.txt
python_colors_linux-0.3.dist-info/RECORD
