Metadata-Version: 2.1
Name: python-colors-linux
Version: 0.3
Summary: Python-Colors For Using To Beautify Your Output With Just Including It As A Simple Variable
Home-page: https://github.com/pmk456/python-colors
Author: Patan Musthakheem
Author-email: patanmusthakheem786@gmail.com
License: UNKNOWN
Project-URL: Bug Tracker, https://github.com/pmk456/python-colors/issues
Platform: UNKNOWN
Classifier: Programming Language :: Python :: 3
Classifier: License :: OSI Approved :: Apache Software License
Classifier: Operating System :: POSIX :: Linux
Requires-Python: >=3.5
